mongojet-0.4.3.dist-info/METADATA
mongojet-0.4.3.dist-info/WHEEL
mongojet-0.4.3.dist-info/licenses/LICENSE.txt
mongojet/__init__.py
mongojet/_client.py
mongojet/_codec.py
mongojet/_collection.py
mongojet/_cursor.py
mongojet/_database.py
mongojet/_gridfs.py
mongojet/_helpers.py
mongojet/_session.py
mongojet/_types.py
mongojet/mongojet.cpython-39-i386-linux-gnu.so
mongojet-0.4.3.dist-info/RECORD
