Metadata-Version: 2.4
Name: mongojet
Version: 0.4.3
Classifier: Development Status :: 4 - Beta
Classifier: Programming Language :: Rust
Classifier: Programming Language :: Python
Classifier: Programming Language :: Python :: 3
Classifier: Programming Language :: Python :: 3 :: Only
Classifier: Programming Language :: Python :: 3.9
Classifier: Programming Language :: Python :: 3.10
Classifier: Programming Language :: Python :: 3.11
Classifier: Programming Language :: Python :: 3.12
Classifier: Programming Language :: Python :: 3.13
Classifier: Programming Language :: Python :: 3.14
Classifier: Operating System :: MacOS
Classifier: Operating System :: Microsoft
Classifier: Operating System :: POSIX :: Linux
Classifier: Topic :: Database
Classifier: Topic :: Database :: Front-Ends
Classifier: Intended Audience :: Developers
Classifier: License :: OSI Approved :: Apache Software License
Requires-Dist: pymongo>=4.6.2
Requires-Dist: typing-extensions>=4.10.0
License-File: LICENSE.txt
Summary: Async MongoDB client for Python
Author-email: Roman Snegirev <snegiryev@gmail.com>
Requires-Python: >=3.9
Project-URL: homepage, https://github.com/romis2012/mongojet
Project-URL: repository, https://github.com/romis2012/mongojet
